pikafish_terminal/__init__.py
pikafish_terminal/_version.py
pikafish_terminal/board.py
pikafish_terminal/cli.py
pikafish_terminal/config.py
pikafish_terminal/config.yaml
pikafish_terminal/difficulty.py
pikafish_terminal/downloader.py
pikafish_terminal/engine.py
pikafish_terminal/game.py
pikafish_terminal/logging_config.py
pikafish_terminal/ui.py
pikafish_terminal-0.0.8.dist-info/licenses/LICENSE
pikafish_terminal-0.0.8.dist-info/METADATA
pikafish_terminal-0.0.8.dist-info/WHEEL
pikafish_terminal-0.0.8.dist-info/entry_points.txt
pikafish_terminal-0.0.8.dist-info/top_level.txt
pikafish_terminal-0.0.8.dist-info/RECORD
