Metadata-Version: 2.4
Name: pikafish-terminal
Version: 0.0.8
Summary: A terminal-based Xiangqi (Chinese Chess) game powered by the Pikafish engine
Author: Pikafish Terminal Contributors
License: MIT License
Project-URL: Homepage, https://github.com/midstreeeam/pikafish-terminal
Project-URL: Repository, https://github.com/midstreeeam/pikafish-terminal
Project-URL: Issues, https://github.com/midstreeeam/pikafish-terminal/issues
Keywords: xiangqi,chinese-chess,chess,game,terminal,pikafish
Classifier: Development Status :: 4 - Beta
Classifier: Environment :: Console
Classifier: Intended Audience :: End Users/Desktop
Classifier: Operating System :: OS Independent
Classifier: Programming Language :: Python :: 3
Classifier: Programming Language :: Python :: 3.8
Classifier: Programming Language :: Python :: 3.9
Classifier: Programming Language :: Python :: 3.10
Classifier: Programming Language :: Python :: 3.11
Classifier: Programming Language :: Python :: 3.12
Classifier: Topic :: Games/Entertainment :: Board Games
Classifier: Topic :: Games/Entertainment :: Turn Based Strategy
Requires-Python: >=3.8
License-File: LICENSE
Requires-Dist: requests>=2.25.0
Requires-Dist: colorama>=0.4.0
Requires-Dist: urllib3>=1.26.0
Requires-Dist: py7zr>=0.20.0
Requires-Dist: tqdm>=4.60.0
Requires-Dist: pyyaml>=6.0.2
Provides-Extra: dev
Requires-Dist: pytest>=6.0; extra == "dev"
Requires-Dist: black>=22.0; extra == "dev"
Requires-Dist: flake8>=4.0; extra == "dev"
Requires-Dist: mypy>=0.900; extra == "dev"
Dynamic: license-file
